image_cleaner/__init__.py
image_cleaner/cli.py
image_cleaner-0.1.3.dist-info/LICENSE
image_cleaner-0.1.3.dist-info/METADATA
image_cleaner-0.1.3.dist-info/WHEEL
image_cleaner-0.1.3.dist-info/entry_points.txt
image_cleaner-0.1.3.dist-info/top_level.txt
image_cleaner-0.1.3.dist-info/RECORD
