Metadata-Version: 2.1
Name: image-cleaner
Version: 0.1.3
Summary: remove metadata from images to enhance privacy
Home-page: https://github.com/MartinThoma/image_cleaner
Author: Martin Thoma
Author-email: info@martin-thoma.de
Maintainer: Martin Thoma
Maintainer-email: info@martin-thoma.de
License: MIT
Download-URL: https://github.com/MartinThoma/image_cleaner
Keywords: privacy,metadata,images,exif
Platform: Linux
Platform: MacOS X
Platform: Windows
Classifier: Development Status :: 7 - Inactive
Classifier: Programming Language :: Python :: 3
Classifier: Programming Language :: Python :: 3 :: Only
Classifier: Programming Language :: Python :: 3.7
Classifier: Programming Language :: Python :: 3.8
Classifier: Programming Language :: Python :: 3.9
Classifier: Topic :: Utilities
Requires-Python: >=3.0
Requires-Dist: Pillow
